formatist.py
formatist-0.0.2.dist-info/WHEEL
formatist-0.0.2.dist-info/RECORD
formatist-0.0.2.dist-info/METADATA
formatist-0.0.2.dist-info/top_level.txt
formatist-0.0.2.dist-info/DESCRIPTION.rst
formatist-0.0.2.dist-info/metadata.json
