Metadata-Version: 2.0
Name: formatist
Version: 0.0.2
Summary: Converts %-style format strings to newer {}-style
Home-page: https://github.com/moreati/formatist
Author: Glyph
Author-email: glyph@twistedmatrix.com
License: MIT
Keywords: string format pep3101 percent braces
Platform: UNKNOWN
Classifier: Development Status :: 3 - Alpha
Classifier: Intended Audience :: Developers
Classifier: License :: OSI Approved :: MIT License
Classifier: Programming Language :: Python :: 2
Classifier: Programming Language :: Python :: 2.6
Classifier: Programming Language :: Python :: 2.7
Classifier: Programming Language :: Python :: 3
Classifier: Programming Language :: Python :: 3.2
Classifier: Programming Language :: Python :: 3.3
Classifier: Programming Language :: Python :: 3.4
Classifier: Programming Language :: Python :: 3.5
